sound_fuzz/__init__.py
sound_fuzz/engine.py
sound_fuzz/string.py
sound_fuzz-1.0.0.dist-info/METADATA
sound_fuzz-1.0.0.dist-info/WHEEL
sound_fuzz-1.0.0.dist-info/top_level.txt
sound_fuzz-1.0.0.dist-info/RECORD
