Metadata-Version: 2.1
Name: sound-fuzz
Version: 1.0.0
Summary: UNKNOWN
Home-page: UNKNOWN
Author: Narendrakumar G S, M V Pranav
Author-email: narensubbu1@gmail.com, pranavmvp@gmail.com
License: UNKNOWN
Project-URL: Documentation, https://github.com/Naren210/sound-fuzz#readme
Project-URL: Source, https://github.com/Naren210/sound-fuzz
Project-URL: Tracker, https://github.com/Naren210/sound-fuzz/issues
Platform: UNKNOWN
Classifier: Development Status :: 3 - Alpha
Classifier: Intended Audience :: Developers
Classifier: Intended Audience :: System Administrators
Classifier: License :: OSI Approved :: MIT License
Classifier: Operating System :: OS Independent
Classifier: Programming Language :: Python :: 3
Requires-Python: >=3.8
Requires-Dist: fuzzywuzzy
Requires-Dist: py4Soundex
